{"cameraMode":{"drawMode":0,"name":"Shaded","section":"Shading Mode"},"sceneLighting":true,"audioPlay":false,"sceneViewState":{"m_AlwaysRefresh":false,"showFog":true,"showSkybox":true,"showFlares":true,"showImageEffects":true,"showParticleSystems":true,"showVisualEffectGraphs":true,"m_FxEnabled":true},"in2DMode":false,"pivot":{"x":-2.6696994304656984,"y":-0.9626630544662476,"z":18.416654586791993},"rotation":{"x":0.06450290977954865,"y":0.038627929985523227,"z":-0.002543799579143524,"w":0.9971486330032349},"size":8.011041641235352,"orthographic":false}